nbrsessionproxy/__init__.py
nbrsessionproxy/handlers.py
nbrsessionproxy/static/tree.js
nbrsessionproxy-0.8.0.dist-info/DESCRIPTION.rst
nbrsessionproxy-0.8.0.dist-info/METADATA
nbrsessionproxy-0.8.0.dist-info/RECORD
nbrsessionproxy-0.8.0.dist-info/WHEEL
nbrsessionproxy-0.8.0.dist-info/metadata.json
nbrsessionproxy-0.8.0.dist-info/top_level.txt
