Metadata-Version: 2.0
Name: nbrsessionproxy
Version: 0.8.0
Summary: Jupyter extension to proxy RStudio's rsession
Home-page: https://github.com/jupyterhub/nbrsessionproxy
Author: Ryan Lovett
Author-email: UNKNOWN
License: UNKNOWN
Keywords: Jupyter
Platform: UNKNOWN
Classifier: Framework :: Jupyter
Requires-Dist: notebook
Requires-Dist: nbserverproxy (>=0.8.8)
